inspari/logging/__init__.py
inspari/logging/configuration.py
inspari/logging/pythonjsonlogger/__init__.py
inspari/logging/pythonjsonlogger/core.py
inspari/logging/pythonjsonlogger/defaults.py
inspari/logging/pythonjsonlogger/exception.py
inspari/logging/pythonjsonlogger/json.py
inspari/logging/pythonjsonlogger/msgspec.py
inspari/logging/pythonjsonlogger/orjson.py
inspari/logging/pythonjsonlogger/py.typed
inspari/logging/pythonjsonlogger/utils.py
inspari/logging/streamlogs.py
inspari/logging/utils.py
inspari_logging-0.1.8.dist-info/METADATA
inspari_logging-0.1.8.dist-info/WHEEL
inspari_logging-0.1.8.dist-info/entry_points.txt
inspari_logging-0.1.8.dist-info/RECORD
