Metadata-Version: 2.3
Name: inspari_logging
Version: 0.1.8
Summary: Inspari logging utilities
License: MIT
Author: emilhe
Author-email: emil.h.eriksen@gmail.com
Requires-Python: >=3.11,<4.0
Classifier: License :: OSI Approved :: MIT License
Classifier: Programming Language :: Python :: 3
Classifier: Programming Language :: Python :: 3.11
Classifier: Programming Language :: Python :: 3.12
Classifier: Programming Language :: Python :: 3.13
Requires-Dist: azure-identity (>=1.19.0,<2.0.0)
Requires-Dist: azure-storage-blob (>=12.24.0,<13.0.0)
Requires-Dist: colorama (>=0.4.6,<0.5.0)
Requires-Dist: inspari-config (>=0.1.5,<0.2.0)
Requires-Dist: pydantic (>=2.10.1,<3.0.0)
Requires-Dist: typer (>=0.13.1,<0.14.0)
